{"NEARUSDT": {"finalScore": 323, "scanStreak": 3}, "SAHARAUSDT": {"finalScore": 318, "scanStreak": 3}, "SIRENUSDT": {"finalScore": 305, "scanStreak": 3}, "ROBOUSDT": {"finalScore": 303, "scanStreak": 2}, "OPNUSDT": {"finalScore": 298, "scanStreak": 2}, "KAVAUSDT": {"finalScore": 292, "scanStreak": 2}, "LYNUSDT": {"finalScore": 277, "scanStreak": 3}, "GRASSUSDT": {"finalScore": 271, "scanStreak": 2}, "BNBUSDT": {"finalScore": 253, "scanStreak": 2}, "DOTUSDT": {"finalScore": 218, "scanStreak": 1}}